pygments_anyscript/BM_constants.txt
pygments_anyscript/BM_parameters.txt
pygments_anyscript/__init__.py
pygments_anyscript/classes.txt
pygments_anyscript/functions.txt
pygments_anyscript/globals.txt
pygments_anyscript-1.5.0.dist-info/entry_points.txt
pygments_anyscript-1.5.0.dist-info/licenses/LICENSE
pygments_anyscript-1.5.0.dist-info/WHEEL
pygments_anyscript-1.5.0.dist-info/METADATA
pygments_anyscript-1.5.0.dist-info/RECORD
