Metadata-Version: 2.4
Name: pygments_anyscript
Version: 1.5.0
Summary: Pygments lexer and style for the AnyScript language. AnyScript is the
Author-email: Morten Enemark Lund <mel@anybodytech.com>
Requires-Python: >=3.7
Classifier: License :: OSI Approved :: MIT License
License-File: LICENSE
Requires-Dist: pygments
Requires-Dist: pytest ; extra == "test"
Project-URL: Home, https://github.com/AnyBody/pygments-anyscript
Provides-Extra: test
